pyaprsfi/__init__.py
pyaprsfi/__main__.py
pyaprsfi/api.py
pyaprsfi/exceptions/__init__.py
pyaprsfi/exceptions/api_key_exception.py
pyaprsfi/exceptions/request_exception.py
pyaprsfi-1.0.0.dist-info/LICENSE
pyaprsfi-1.0.0.dist-info/WHEEL
pyaprsfi-1.0.0.dist-info/METADATA
pyaprsfi-1.0.0.dist-info/RECORD
