Metadata-Version: 2.1
Name: pyaprsfi
Version: 1.0.0
Summary: An aprs.fi API client for Python
License: GPLv3
Author: Evan Pratten
Author-email: ewpratten@gmail.com
Requires-Python: >=3.9,<4.0
Classifier: License :: Other/Proprietary License
Classifier: Programming Language :: Python :: 3
Classifier: Programming Language :: Python :: 3.9
Requires-Dist: requests (>=2.25.1,<3.0.0)
